{
  "namespaces": [],
  "tables": [
    {
      "columns": {
        "id": {
          "name": "id",
          "type": "integer",
          "unsigned": false,
          "autoincrement": true,
          "primary": true,
          "nullable": false,
          "length": null,
          "mappedType": "integer"
        },
        "name": {
          "name": "name",
          "type": "text",
          "unsigned": false,
          "autoincrement": false,
          "primary": false,
          "nullable": false,
          "length": null,
          "mappedType": "text"
        },
        "description": {
          "name": "description",
          "type": "text",
          "unsigned": false,
          "autoincrement": false,
          "primary": false,
          "nullable": true,
          "length": null,
          "mappedType": "text"
        },
        "created_at": {
          "name": "created_at",
          "type": "datetime",
          "unsigned": false,
          "autoincrement": false,
          "primary": false,
          "nullable": false,
          "length": null,
          "mappedType": "datetime"
        }
      },
      "name": "category",
      "indexes": [
        {
          "columnNames": [
            "name"
          ],
          "composite": false,
          "keyName": "category_name_unique",
          "constraint": true,
          "primary": false,
          "unique": true
        },
        {
          "keyName": "primary",
          "columnNames": [
            "id"
          ],
          "composite": false,
          "constraint": true,
          "primary": true,
          "unique": true
        }
      ],
      "checks": [],
      "foreignKeys": {},
      "nativeEnums": {}
    },
    {
      "columns": {
        "id": {
          "name": "id",
          "type": "integer",
          "unsigned": false,
          "autoincrement": true,
          "primary": true,
          "nullable": false,
          "length": null,
          "mappedType": "integer"
        },
        "name": {
          "name": "name",
          "type": "text",
          "unsigned": false,
          "autoincrement": false,
          "primary": false,
          "nullable": false,
          "length": null,
          "mappedType": "text"
        },
        "description": {
          "name": "description",
          "type": "text",
          "unsigned": false,
          "autoincrement": false,
          "primary": false,
          "nullable": true,
          "length": null,
          "mappedType": "text"
        },
        "price": {
          "name": "price",
          "type": "integer",
          "unsigned": false,
          "autoincrement": false,
          "primary": false,
          "nullable": false,
          "length": null,
          "mappedType": "integer"
        },
        "category_id": {
          "name": "category_id",
          "type": "integer",
          "unsigned": false,
          "autoincrement": false,
          "primary": false,
          "nullable": false,
          "length": null,
          "mappedType": "integer"
        },
        "created_at": {
          "name": "created_at",
          "type": "datetime",
          "unsigned": false,
          "autoincrement": false,
          "primary": false,
          "nullable": false,
          "length": null,
          "mappedType": "datetime"
        },
        "updated_at": {
          "name": "updated_at",
          "type": "datetime",
          "unsigned": false,
          "autoincrement": false,
          "primary": false,
          "nullable": false,
          "length": null,
          "mappedType": "datetime"
        }
      },
      "name": "product",
      "indexes": [
        {
          "columnNames": [
            "category_id"
          ],
          "composite": false,
          "keyName": "product_category_id_index",
          "constraint": false,
          "primary": false,
          "unique": false
        },
        {
          "keyName": "primary",
          "columnNames": [
            "id"
          ],
          "composite": false,
          "constraint": true,
          "primary": true,
          "unique": true
        }
      ],
      "checks": [],
      "foreignKeys": {
        "product_category_id_foreign": {
          "constraintName": "product_category_id_foreign",
          "columnNames": [
            "category_id"
          ],
          "localTableName": "product",
          "referencedColumnNames": [
            "id"
          ],
          "referencedTableName": "category",
          "updateRule": "cascade"
        }
      },
      "nativeEnums": {}
    },
    {
      "columns": {
        "id": {
          "name": "id",
          "type": "integer",
          "unsigned": false,
          "autoincrement": true,
          "primary": true,
          "nullable": false,
          "length": null,
          "mappedType": "integer"
        },
        "email": {
          "name": "email",
          "type": "text",
          "unsigned": false,
          "autoincrement": false,
          "primary": false,
          "nullable": false,
          "length": null,
          "mappedType": "text"
        },
        "password": {
          "name": "password",
          "type": "text",
          "unsigned": false,
          "autoincrement": false,
          "primary": false,
          "nullable": false,
          "length": null,
          "mappedType": "text"
        },
        "created_at": {
          "name": "created_at",
          "type": "datetime",
          "unsigned": false,
          "autoincrement": false,
          "primary": false,
          "nullable": false,
          "length": null,
          "mappedType": "datetime"
        },
        "updated_at": {
          "name": "updated_at",
          "type": "datetime",
          "unsigned": false,
          "autoincrement": false,
          "primary": false,
          "nullable": false,
          "length": null,
          "mappedType": "datetime"
        }
      },
      "name": "user",
      "indexes": [
        {
          "columnNames": [
            "email"
          ],
          "composite": false,
          "keyName": "user_email_unique",
          "constraint": true,
          "primary": false,
          "unique": true
        },
        {
          "keyName": "primary",
          "columnNames": [
            "id"
          ],
          "composite": false,
          "constraint": true,
          "primary": true,
          "unique": true
        }
      ],
      "checks": [],
      "foreignKeys": {},
      "nativeEnums": {}
    },
    {
      "columns": {
        "id": {
          "name": "id",
          "type": "integer",
          "unsigned": false,
          "autoincrement": true,
          "primary": true,
          "nullable": false,
          "length": null,
          "mappedType": "integer"
        },
        "session_id": {
          "name": "session_id",
          "type": "text",
          "unsigned": false,
          "autoincrement": false,
          "primary": false,
          "nullable": false,
          "length": null,
          "mappedType": "text"
        },
        "user_id": {
          "name": "user_id",
          "type": "integer",
          "unsigned": false,
          "autoincrement": false,
          "primary": false,
          "nullable": false,
          "length": null,
          "mappedType": "integer"
        },
        "expires_at": {
          "name": "expires_at",
          "type": "datetime",
          "unsigned": false,
          "autoincrement": false,
          "primary": false,
          "nullable": false,
          "length": null,
          "mappedType": "datetime"
        },
        "created_at": {
          "name": "created_at",
          "type": "datetime",
          "unsigned": false,
          "autoincrement": false,
          "primary": false,
          "nullable": false,
          "length": null,
          "mappedType": "datetime"
        }
      },
      "name": "session",
      "indexes": [
        {
          "columnNames": [
            "session_id"
          ],
          "composite": false,
          "keyName": "session_session_id_unique",
          "constraint": true,
          "primary": false,
          "unique": true
        },
        {
          "columnNames": [
            "user_id"
          ],
          "composite": false,
          "keyName": "session_user_id_index",
          "constraint": false,
          "primary": false,
          "unique": false
        },
        {
          "keyName": "primary",
          "columnNames": [
            "id"
          ],
          "composite": false,
          "constraint": true,
          "primary": true,
          "unique": true
        }
      ],
      "checks": [],
      "foreignKeys": {
        "session_user_id_foreign": {
          "constraintName": "session_user_id_foreign",
          "columnNames": [
            "user_id"
          ],
          "localTableName": "session",
          "referencedColumnNames": [
            "id"
          ],
          "referencedTableName": "user",
          "updateRule": "cascade"
        }
      },
      "nativeEnums": {}
    },
    {
      "columns": {
        "id": {
          "name": "id",
          "type": "integer",
          "unsigned": false,
          "autoincrement": true,
          "primary": true,
          "nullable": false,
          "length": null,
          "mappedType": "integer"
        },
        "user_id": {
          "name": "user_id",
          "type": "integer",
          "unsigned": false,
          "autoincrement": false,
          "primary": false,
          "nullable": false,
          "length": null,
          "mappedType": "integer"
        },
        "total": {
          "name": "total",
          "type": "integer",
          "unsigned": false,
          "autoincrement": false,
          "primary": false,
          "nullable": false,
          "length": null,
          "mappedType": "integer"
        },
        "status": {
          "name": "status",
          "type": "text",
          "unsigned": false,
          "autoincrement": false,
          "primary": false,
          "nullable": false,
          "length": null,
          "default": "'pending'",
          "mappedType": "text"
        },
        "created_at": {
          "name": "created_at",
          "type": "datetime",
          "unsigned": false,
          "autoincrement": false,
          "primary": false,
          "nullable": false,
          "length": null,
          "mappedType": "datetime"
        },
        "updated_at": {
          "name": "updated_at",
          "type": "datetime",
          "unsigned": false,
          "autoincrement": false,
          "primary": false,
          "nullable": false,
          "length": null,
          "mappedType": "datetime"
        }
      },
      "name": "order",
      "indexes": [
        {
          "columnNames": [
            "user_id"
          ],
          "composite": false,
          "keyName": "order_user_id_index",
          "constraint": false,
          "primary": false,
          "unique": false
        },
        {
          "keyName": "primary",
          "columnNames": [
            "id"
          ],
          "composite": false,
          "constraint": true,
          "primary": true,
          "unique": true
        }
      ],
      "checks": [],
      "foreignKeys": {
        "order_user_id_foreign": {
          "constraintName": "order_user_id_foreign",
          "columnNames": [
            "user_id"
          ],
          "localTableName": "order",
          "referencedColumnNames": [
            "id"
          ],
          "referencedTableName": "user",
          "updateRule": "cascade"
        }
      },
      "nativeEnums": {}
    },
    {
      "columns": {
        "id": {
          "name": "id",
          "type": "integer",
          "unsigned": false,
          "autoincrement": true,
          "primary": true,
          "nullable": false,
          "length": null,
          "mappedType": "integer"
        },
        "order_id": {
          "name": "order_id",
          "type": "integer",
          "unsigned": false,
          "autoincrement": false,
          "primary": false,
          "nullable": false,
          "length": null,
          "mappedType": "integer"
        },
        "product_id": {
          "name": "product_id",
          "type": "integer",
          "unsigned": false,
          "autoincrement": false,
          "primary": false,
          "nullable": false,
          "length": null,
          "mappedType": "integer"
        },
        "quantity": {
          "name": "quantity",
          "type": "integer",
          "unsigned": false,
          "autoincrement": false,
          "primary": false,
          "nullable": false,
          "length": null,
          "mappedType": "integer"
        },
        "price": {
          "name": "price",
          "type": "integer",
          "unsigned": false,
          "autoincrement": false,
          "primary": false,
          "nullable": false,
          "length": null,
          "mappedType": "integer"
        },
        "created_at": {
          "name": "created_at",
          "type": "datetime",
          "unsigned": false,
          "autoincrement": false,
          "primary": false,
          "nullable": false,
          "length": null,
          "mappedType": "datetime"
        }
      },
      "name": "order_item",
      "indexes": [
        {
          "columnNames": [
            "order_id"
          ],
          "composite": false,
          "keyName": "order_item_order_id_index",
          "constraint": false,
          "primary": false,
          "unique": false
        },
        {
          "columnNames": [
            "product_id"
          ],
          "composite": false,
          "keyName": "order_item_product_id_index",
          "constraint": false,
          "primary": false,
          "unique": false
        },
        {
          "keyName": "primary",
          "columnNames": [
            "id"
          ],
          "composite": false,
          "constraint": true,
          "primary": true,
          "unique": true
        }
      ],
      "checks": [],
      "foreignKeys": {
        "order_item_order_id_foreign": {
          "constraintName": "order_item_order_id_foreign",
          "columnNames": [
            "order_id"
          ],
          "localTableName": "order_item",
          "referencedColumnNames": [
            "id"
          ],
          "referencedTableName": "order",
          "updateRule": "cascade"
        },
        "order_item_product_id_foreign": {
          "constraintName": "order_item_product_id_foreign",
          "columnNames": [
            "product_id"
          ],
          "localTableName": "order_item",
          "referencedColumnNames": [
            "id"
          ],
          "referencedTableName": "product",
          "updateRule": "cascade"
        }
      },
      "nativeEnums": {}
    },
    {
      "columns": {
        "id": {
          "name": "id",
          "type": "integer",
          "unsigned": false,
          "autoincrement": true,
          "primary": true,
          "nullable": false,
          "length": null,
          "mappedType": "integer"
        },
        "user_id": {
          "name": "user_id",
          "type": "integer",
          "unsigned": false,
          "autoincrement": false,
          "primary": false,
          "nullable": false,
          "length": null,
          "mappedType": "integer"
        },
        "created_at": {
          "name": "created_at",
          "type": "datetime",
          "unsigned": false,
          "autoincrement": false,
          "primary": false,
          "nullable": false,
          "length": null,
          "mappedType": "datetime"
        },
        "updated_at": {
          "name": "updated_at",
          "type": "datetime",
          "unsigned": false,
          "autoincrement": false,
          "primary": false,
          "nullable": false,
          "length": null,
          "mappedType": "datetime"
        }
      },
      "name": "cart",
      "indexes": [
        {
          "columnNames": [
            "user_id"
          ],
          "composite": false,
          "keyName": "cart_user_id_index",
          "constraint": false,
          "primary": false,
          "unique": false
        },
        {
          "keyName": "primary",
          "columnNames": [
            "id"
          ],
          "composite": false,
          "constraint": true,
          "primary": true,
          "unique": true
        }
      ],
      "checks": [],
      "foreignKeys": {
        "cart_user_id_foreign": {
          "constraintName": "cart_user_id_foreign",
          "columnNames": [
            "user_id"
          ],
          "localTableName": "cart",
          "referencedColumnNames": [
            "id"
          ],
          "referencedTableName": "user",
          "updateRule": "cascade"
        }
      },
      "nativeEnums": {}
    },
    {
      "columns": {
        "id": {
          "name": "id",
          "type": "integer",
          "unsigned": false,
          "autoincrement": true,
          "primary": true,
          "nullable": false,
          "length": null,
          "mappedType": "integer"
        },
        "cart_id": {
          "name": "cart_id",
          "type": "integer",
          "unsigned": false,
          "autoincrement": false,
          "primary": false,
          "nullable": false,
          "length": null,
          "mappedType": "integer"
        },
        "product_id": {
          "name": "product_id",
          "type": "integer",
          "unsigned": false,
          "autoincrement": false,
          "primary": false,
          "nullable": false,
          "length": null,
          "mappedType": "integer"
        },
        "quantity": {
          "name": "quantity",
          "type": "integer",
          "unsigned": false,
          "autoincrement": false,
          "primary": false,
          "nullable": false,
          "length": null,
          "mappedType": "integer"
        },
        "created_at": {
          "name": "created_at",
          "type": "datetime",
          "unsigned": false,
          "autoincrement": false,
          "primary": false,
          "nullable": false,
          "length": null,
          "mappedType": "datetime"
        },
        "updated_at": {
          "name": "updated_at",
          "type": "datetime",
          "unsigned": false,
          "autoincrement": false,
          "primary": false,
          "nullable": false,
          "length": null,
          "mappedType": "datetime"
        }
      },
      "name": "cart_item",
      "indexes": [
        {
          "columnNames": [
            "cart_id"
          ],
          "composite": false,
          "keyName": "cart_item_cart_id_index",
          "constraint": false,
          "primary": false,
          "unique": false
        },
        {
          "columnNames": [
            "product_id"
          ],
          "composite": false,
          "keyName": "cart_item_product_id_index",
          "constraint": false,
          "primary": false,
          "unique": false
        },
        {
          "keyName": "primary",
          "columnNames": [
            "id"
          ],
          "composite": false,
          "constraint": true,
          "primary": true,
          "unique": true
        }
      ],
      "checks": [],
      "foreignKeys": {
        "cart_item_cart_id_foreign": {
          "constraintName": "cart_item_cart_id_foreign",
          "columnNames": [
            "cart_id"
          ],
          "localTableName": "cart_item",
          "referencedColumnNames": [
            "id"
          ],
          "referencedTableName": "cart",
          "updateRule": "cascade"
        },
        "cart_item_product_id_foreign": {
          "constraintName": "cart_item_product_id_foreign",
          "columnNames": [
            "product_id"
          ],
          "localTableName": "cart_item",
          "referencedColumnNames": [
            "id"
          ],
          "referencedTableName": "product",
          "updateRule": "cascade"
        }
      },
      "nativeEnums": {}
    }
  ],
  "nativeEnums": {}
}
